witlog/__init__.py
witlog/base.py
witlog/static.py
witlog/timing/__init__.py
witlog/timing/timing.py
witlog-0.1.4.dist-info/LICENSE
witlog-0.1.4.dist-info/METADATA
witlog-0.1.4.dist-info/WHEEL
witlog-0.1.4.dist-info/top_level.txt
witlog-0.1.4.dist-info/RECORD
