Metadata-Version: 2.1
Name: witlog
Version: 0.1.4
Summary: WitLog is a lightweight zero-overhead static structured log library for researchers.
Author-email: tomorrowdawn <tomorrowdawn@foxmail.com>
License: Apache License
Project-URL: homepage, https://github.com/Tomorrowdawn/WitLog
Project-URL: repository, https://github.com/Tomorrowdawn/WitLog
Keywords: logging,structured,zero-overhead,research
Requires-Python: >=3.10
License-File: LICENSE
Requires-Dist: attrs
Provides-Extra: full
Requires-Dist: attrs ; extra == 'full'
Requires-Dist: torch ; extra == 'full'
Requires-Dist: pandas ; extra == 'full'
